auto_circuit/data.py
auto_circuit/experiment_utils.py
auto_circuit/metrics/area_under_curve.py
auto_circuit/metrics/avoid_edges.py
auto_circuit/metrics/completeness_metrics/same_under_knockouts.py
auto_circuit/metrics/completeness_metrics/train_same_under_knockouts.py
auto_circuit/metrics/official_circuits/circuits/docstring_official.py
auto_circuit/metrics/official_circuits/circuits/greaterthan_official.py
auto_circuit/metrics/official_circuits/circuits/ioi_official.py
auto_circuit/metrics/official_circuits/circuits/sports_players_official.py
auto_circuit/metrics/official_circuits/circuits/tracr/reverse_official.py
auto_circuit/metrics/official_circuits/circuits/tracr/xproportion_official.py
auto_circuit/metrics/official_circuits/measure_roc.py
auto_circuit/metrics/official_circuits/roc_plot.py
auto_circuit/metrics/prune_metrics/answer_diff.py
auto_circuit/metrics/prune_metrics/answer_diff_percent.py
auto_circuit/metrics/prune_metrics/answer_value.py
auto_circuit/metrics/prune_metrics/correct_answer_percent.py
auto_circuit/metrics/prune_metrics/kl_div.py
auto_circuit/metrics/prune_metrics/measure_prune_metrics.py
auto_circuit/metrics/prune_metrics/prune_metrics.py
auto_circuit/metrics/prune_metrics/prune_metrics_plot.py
auto_circuit/metrics/prune_scores_similarity.py
auto_circuit/model_utils/micro_model_utils.py
auto_circuit/model_utils/sparse_autoencoders/autoencoder_training.py
auto_circuit/model_utils/sparse_autoencoders/autoencoder_transformer.py
auto_circuit/model_utils/sparse_autoencoders/sparse_autoencoder.py
auto_circuit/model_utils/task_projectors/projector_transformer.py
auto_circuit/model_utils/task_projectors/task_projector.py
auto_circuit/model_utils/task_projectors/task_projector_training.py
auto_circuit/model_utils/tracr_model_utils.py
auto_circuit/model_utils/transformer_lens_utils.py
auto_circuit/prune.py
auto_circuit/prune_algos/ACDC.py
auto_circuit/prune_algos/activation_magnitude.py
auto_circuit/prune_algos/circuit_probing.py
auto_circuit-1.0.1.dist-info/METADATA
auto_circuit-1.0.1.dist-info/WHEEL
auto_circuit-1.0.1.dist-info/RECORD
