Metadata-Version: 2.1
Name: auto-circuit
Version: 1.0.1
Summary: 
Author: UFO-101
Author-email: josephmiller101@gmail.com
Requires-Python: >=3.10,<4.0
Classifier: Programming Language :: Python :: 3
Classifier: Programming Language :: Python :: 3.10
Classifier: Programming Language :: Python :: 3.11
Classifier: Programming Language :: Python :: 3.12
Requires-Dist: blobfile (>=2.0.2)
Requires-Dist: einops (>=0.6.1)
Requires-Dist: kaleido (==0.2.1)
Requires-Dist: ordered-set (>=4.1.0)
Requires-Dist: plotly (>=5.18.0)
Requires-Dist: torch (>=2.1.1)
Requires-Dist: tracr-pypi (>=1.0.0)
Requires-Dist: transformer-lens (>=1.13.0)
Requires-Dist: vscode-tqdm (>=4.66.2)
Requires-Dist: word2word (>=1.0.0)
